mkdocs_jupyter2/__about__.py
mkdocs_jupyter2/__init__.py
mkdocs_jupyter2/config.py
mkdocs_jupyter2/convert.py
mkdocs_jupyter2/nbconvert2.py
mkdocs_jupyter2/plugin.py
mkdocs_jupyter2/preprocessors.py
mkdocs_jupyter2/utils.py
mkdocs_jupyter2/templates/mkdocs_html/conf.json
mkdocs_jupyter2/templates/mkdocs_html/notebook.html.j2
mkdocs_jupyter2/templates/mkdocs_html/assets/.gitignore
mkdocs_jupyter2/templates/mkdocs_html/assets/clipboard.umd.js
mkdocs_jupyter2/templates/mkdocs_html/assets/dark.js
mkdocs_jupyter2/templates/mkdocs_html/assets/index.css
mkdocs_jupyter2/templates/mkdocs_html/assets/index.js
mkdocs_jupyter2/templates/mkdocs_html/assets/light.js
mkdocs_jupyter2/templates/mkdocs_html/assets/theme-dark.css
mkdocs_jupyter2/templates/mkdocs_html/assets/theme-light.css
mkdocs_jupyter2/templates/mkdocs_md/conf.json
mkdocs_jupyter2/templates/mkdocs_md/md-no-codecell.md.j2
mkdocs_jupyter2/tests/__init__.py
mkdocs_jupyter2/tests/test_base_usage.py
mkdocs_jupyter2/tests/test_pkg.py
mkdocs_jupyter2/tests/test_toc.py
mkdocs_jupyter2/tests/mkdocs/base-with-mds.yml
mkdocs_jupyter2/tests/mkdocs/base-with-nbs-failure.yml
mkdocs_jupyter2/tests/mkdocs/base-with-nbs-pys.yml
mkdocs_jupyter2/tests/mkdocs/base-with-nbs.yml
mkdocs_jupyter2/tests/mkdocs/base-with-pys.yml
mkdocs_jupyter2/tests/mkdocs/base-without-nbs.yml
mkdocs_jupyter2/tests/mkdocs/material-execute-and-remove-output.yml
mkdocs_jupyter2/tests/mkdocs/material-execute-ignore.yml
mkdocs_jupyter2/tests/mkdocs/material-with-mds.yml
mkdocs_jupyter2/tests/mkdocs/material-with-nbs-pys.yml
mkdocs_jupyter2/tests/mkdocs/material-with-nbs.yml
mkdocs_jupyter2/tests/mkdocs/material-with-pys.yml
mkdocs_jupyter2/tests/mkdocs/docs/backquote_toc_test.ipynb
mkdocs_jupyter2/tests/mkdocs/docs/demo-jupytext.md
mkdocs_jupyter2/tests/mkdocs/docs/demo-script.py
mkdocs_jupyter2/tests/mkdocs/docs/demo.ipynb
mkdocs_jupyter2/tests/mkdocs/docs/fail.ipynb
mkdocs_jupyter2/tests/mkdocs/docs/index.md
mkdocs_jupyter2/tests/mkdocs/docs/ruby.ipynb
mkdocs_jupyter2-0.25.2.dist-info/METADATA
mkdocs_jupyter2-0.25.2.dist-info/WHEEL
mkdocs_jupyter2-0.25.2.dist-info/entry_points.txt
mkdocs_jupyter2-0.25.2.dist-info/licenses/LICENSE.txt
mkdocs_jupyter2-0.25.2.dist-info/RECORD
